pyMSHRF/HRF_calculator.py
pyMSHRF/__init__.py
pyMSHRF/derivatization.py
pyMSHRF/version.py
pyMSHRF/file_io/__init__.py
pyMSHRF/file_io/lbm2_file.py
pyMSHRF/file_io/mgf_file.py
pyMSHRF/file_io/msp_file.py
pyMSHRF/file_io/mzml_file.py
pyMSHRF/file_io/shared.py
pyMSHRF/file_io/spec_file.py
pyMSHRF/pyisopach/__init__.py
pyMSHRF/pyisopach/element.py
pyMSHRF/pyisopach/molecule.py
pyMSHRF/pyisopach/periodic_table.py
pyMSHRF-0.3.0.dist-info/LICENSE
pyMSHRF-0.3.0.dist-info/METADATA
pyMSHRF-0.3.0.dist-info/WHEEL
pyMSHRF-0.3.0.dist-info/top_level.txt
pyMSHRF-0.3.0.dist-info/RECORD
